{
    "id": 369603883,
    "node_id": "MDEwOlJlcG9zaXRvcnkzNjk2MDM4ODM=",
    "name": "Activity-Tracker",
    "full_name": "OpenLake/Activity-Tracker",
    "private": false,
    "owner": {
        "login": "OpenLake",
        "id": 61535687,
        "node_id": "MDEyOk9yZ2FuaXphdGlvbjYxNTM1Njg3",
        "avatar_url": "https://avatars.githubusercontent.com/u/61535687?v=4",
        "gravatar_id": "",
        "url": "https://api.github.com/users/OpenLake",
        "html_url": "https://github.com/OpenLake",
        "followers_url": "https://api.github.com/users/OpenLake/followers",
        "following_url": "https://api.github.com/users/OpenLake/following{/other_user}",
        "gists_url": "https://api.github.com/users/OpenLake/gists{/gist_id}",
        "starred_url": "https://api.github.com/users/OpenLake/starred{/owner}{/repo}",
        "subscriptions_url": "https://api.github.com/users/OpenLake/subscriptions",
        "organizations_url": "https://api.github.com/users/OpenLake/orgs",
        "repos_url": "https://api.github.com/users/OpenLake/repos",
        "events_url": "https://api.github.com/users/OpenLake/events{/privacy}",
        "received_events_url": "https://api.github.com/users/OpenLake/received_events",
        "type": "Organization",
        "site_admin": false
    },
    "html_url": "https://github.com/OpenLake/Activity-Tracker",
    "description": "A cross-platform solution to discover how you spend your digital life. 🕵️‍♂️⌛",
    "fork": false,
    "url": "https://api.github.com/repos/OpenLake/Activity-Tracker",
    "forks_url": "https://api.github.com/repos/OpenLake/Activity-Tracker/forks",
    "keys_url": "https://api.github.com/repos/OpenLake/Activity-Tracker/keys{/key_id}",
    "collaborators_url": "https://api.github.com/repos/OpenLake/Activity-Tracker/collaborators{/collaborator}",
    "teams_url": "https://api.github.com/repos/OpenLake/Activity-Tracker/teams",
    "hooks_url": "https://api.github.com/repos/OpenLake/Activity-Tracker/hooks",
    "issue_events_url": "https://api.github.com/repos/OpenLake/Activity-Tracker/issues/events{/number}",
    "events_url": "https://api.github.com/repos/OpenLake/Activity-Tracker/events",
    "assignees_url": "https://api.github.com/repos/OpenLake/Activity-Tracker/assignees{/user}",
    "branches_url": "https://api.github.com/repos/OpenLake/Activity-Tracker/branches{/branch}",
    "tags_url": "https://api.github.com/repos/OpenLake/Activity-Tracker/tags",
    "blobs_url": "https://api.github.com/repos/OpenLake/Activity-Tracker/git/blobs{/sha}",
    "git_tags_url": "https://api.github.com/repos/OpenLake/Activity-Tracker/git/tags{/sha}",
    "git_refs_url": "https://api.github.com/repos/OpenLake/Activity-Tracker/git/refs{/sha}",
    "trees_url": "https://api.github.com/repos/OpenLake/Activity-Tracker/git/trees{/sha}",
    "statuses_url": "https://api.github.com/repos/OpenLake/Activity-Tracker/statuses/{sha}",
    "languages_url": "https://api.github.com/repos/OpenLake/Activity-Tracker/languages",
    "stargazers_url": "https://api.github.com/repos/OpenLake/Activity-Tracker/stargazers",
    "contributors_url": "https://api.github.com/repos/OpenLake/Activity-Tracker/contributors",
    "subscribers_url": "https://api.github.com/repos/OpenLake/Activity-Tracker/subscribers",
    "subscription_url": "https://api.github.com/repos/OpenLake/Activity-Tracker/subscription",
    "commits_url": "https://api.github.com/repos/OpenLake/Activity-Tracker/commits{/sha}",
    "git_commits_url": "https://api.github.com/repos/OpenLake/Activity-Tracker/git/commits{/sha}",
    "comments_url": "https://api.github.com/repos/OpenLake/Activity-Tracker/comments{/number}",
    "issue_comment_url": "https://api.github.com/repos/OpenLake/Activity-Tracker/issues/comments{/number}",
    "contents_url": "https://api.github.com/repos/OpenLake/Activity-Tracker/contents/{+path}",
    "compare_url": "https://api.github.com/repos/OpenLake/Activity-Tracker/compare/{base}...{head}",
    "merges_url": "https://api.github.com/repos/OpenLake/Activity-Tracker/merges",
    "archive_url": "https://api.github.com/repos/OpenLake/Activity-Tracker/{archive_format}{/ref}",
    "downloads_url": "https://api.github.com/repos/OpenLake/Activity-Tracker/downloads",
    "issues_url": "https://api.github.com/repos/OpenLake/Activity-Tracker/issues{/number}",
    "pulls_url": "https://api.github.com/repos/OpenLake/Activity-Tracker/pulls{/number}",
    "milestones_url": "https://api.github.com/repos/OpenLake/Activity-Tracker/milestones{/number}",
    "notifications_url": "https://api.github.com/repos/OpenLake/Activity-Tracker/notifications{?since,all,participating}",
    "labels_url": "https://api.github.com/repos/OpenLake/Activity-Tracker/labels{/name}",
    "releases_url": "https://api.github.com/repos/OpenLake/Activity-Tracker/releases{/id}",
    "deployments_url": "https://api.github.com/repos/OpenLake/Activity-Tracker/deployments",
    "created_at": "2021-05-21T17:09:17Z",
    "updated_at": "2023-06-19T21:36:54Z",
    "pushed_at": "2022-05-24T11:33:48Z",
    "git_url": "git://github.com/OpenLake/Activity-Tracker.git",
    "ssh_url": "git@github.com:OpenLake/Activity-Tracker.git",
    "clone_url": "https://github.com/OpenLake/Activity-Tracker.git",
    "svn_url": "https://github.com/OpenLake/Activity-Tracker",
    "homepage": "",
    "size": 855,
    "stargazers_count": 19,
    "watchers_count": 19,
    "language": "JavaScript",
    "has_issues": true,
    "has_projects": true,
    "has_downloads": true,
    "has_wiki": true,
    "has_pages": false,
    "has_discussions": false,
    "forks_count": 30,
    "mirror_url": null,
    "archived": false,
    "disabled": false,
    "open_issues_count": 10,
    "license": null,
    "allow_forking": true,
    "is_template": false,
    "web_commit_signoff_required": false,
    "topics": [
        "analytics",
        "android",
        "flutter",
        "hacktoberfest",
        "javascript",
        "nodejs",
        "react",
        "self-hosted"
    ],
    "visibility": "public",
    "forks": 30,
    "open_issues": 10,
    "watchers": 19,
    "default_branch": "main",
    "temp_clone_token": null,
    "organization": {
        "login": "OpenLake",
        "id": 61535687,
        "node_id": "MDEyOk9yZ2FuaXphdGlvbjYxNTM1Njg3",
        "avatar_url": "https://avatars.githubusercontent.com/u/61535687?v=4",
        "gravatar_id": "",
        "url": "https://api.github.com/users/OpenLake",
        "html_url": "https://github.com/OpenLake",
        "followers_url": "https://api.github.com/users/OpenLake/followers",
        "following_url": "https://api.github.com/users/OpenLake/following{/other_user}",
        "gists_url": "https://api.github.com/users/OpenLake/gists{/gist_id}",
        "starred_url": "https://api.github.com/users/OpenLake/starred{/owner}{/repo}",
        "subscriptions_url": "https://api.github.com/users/OpenLake/subscriptions",
        "organizations_url": "https://api.github.com/users/OpenLake/orgs",
        "repos_url": "https://api.github.com/users/OpenLake/repos",
        "events_url": "https://api.github.com/users/OpenLake/events{/privacy}",
        "received_events_url": "https://api.github.com/users/OpenLake/received_events",
        "type": "Organization",
        "site_admin": false
    },
    "network_count": 30,
    "subscribers_count": 1
}